s3cdsapi/__init__.py
s3cdsapi/main.py
s3cdsapi/models.py
s3cdsapi/product_params.py
s3cdsapi/utils.py
s3cdsapi-0.2.13.dist-info/METADATA
s3cdsapi-0.2.13.dist-info/WHEEL
s3cdsapi-0.2.13.dist-info/licenses/LICENSE
s3cdsapi-0.2.13.dist-info/RECORD
