Metadata-Version: 2.4
Name: s3cdsapi
Version: 0.2.13
Summary: cdsapi for s3 and local files
Project-URL: Documentation, https://mullenkamp.github.io/s3cdsapi/
Project-URL: Source, https://github.com/mullenkamp/s3cdsapi
Author-email: mullenkamp <mullenkamp1@gmail.com>
License-File: LICENSE
Classifier: Programming Language :: Python :: 3 :: Only
Requires-Python: >=3.10
Requires-Dist: booklet>=0.7.8
Requires-Dist: msgspec
Requires-Dist: numpy
Requires-Dist: pandas<3
Requires-Dist: s3func>=0.7.0
Requires-Dist: urllib3>=2
